Workbook
Name ANOS: '2'!$D$15
Name APORTE: '2'!$D$14
Name CINCO_ANOS: '2'!$A$24
Name dez: '2'!$A$25
Name DEZ_ANOS: '2'!$A$24
Name DIVIDENDOS: '2'!$D$18
Name DOIS_ANOS: '2'!$A$23
Name PATRIMONIO: '2'!$D$17
Name RENDIMENTO_CARTEIRA: '2'!$D$9
Name RENDIMETO_MES: '2'!$D$16
Name SUJESTÃO_RENDIMENTO: '2'!$D$10
Name TRINTA_ANOS: '2'!$A$27
Name valor_a_Ser_investido_no_mes: '2'!$C$33
Name VINTE_ANOS: '2'!$A$26

Sheet 2
B7: CONFIGURAÇÕES
B8: SALÁRIO | D8: 1200
B9: RENDIMENTO CARTEIRA | D9: 0.0108
B10: SUJESTÃO DE INVESTIMENTO | D10: =D8*30% -> 360
B13: INVESTIMENTO MENSAL
B14: Quanto Tempo investir | D14: 1300
B15: Por quantos anos | D15: 5
B16: taxa de rendimento Mensal | D16: 0.01079
B17: Patrimonio Acumulado | D17: =FV(RENDIMETO_MES,ANOS*12,APORTE*-1) -> 108909.99
B18: Dividendos mensais | D18: =D17*$D$9 -> 1176.2279
B22: CENÁRIOS | D22: DIVIDENDOS
A23: 2 | B23: Quanto teria em 2 Anos ? | C23: =FV($D$16,DOIS_ANOS*12,$D$14*-1) -> 35395.915 | D23: =C23*RENDIMENTO_CARTEIRA -> 382.27589
A24: 5 | B24: Quanto em 5 anos | C24: =FV($D$16,CINCO_ANOS*12,$D$14*-1) -> 108909.99 | D24: =C24*RENDIMENTO_CARTEIRA -> 1176.2279
A25: 10 | B25: Quanto em 10 anos | C25: =FV($D$16,dez*12,$D$14*-1) -> 316269.48 | D25: =C25*RENDIMENTO_CARTEIRA -> 3415.7103
A26: 20 | B26: Quanto em 20 Anos | C26: =FV($D$16,VINTE_ANOS*12,$D$14*-1) -> 1462757.9 | D26: =C26*RENDIMENTO_CARTEIRA -> 15797.786
A27: 30 | B27: Quanto em 30 anos | C27: =FV($D$16,TRINTA_ANOS*12,$D$14*-1) -> 5618820.6 | D27: =C27*RENDIMENTO_CARTEIRA -> 60683.262
B32: PERFIL | C32: AGRESSIVO
B33: VALOR A SER INVESTIDO POR MÊS | C33: =APORTE -> 1300
B35: TIPO DE FIL | C35: PERCENTUAL SUJERIDO | D35: VALORES
B36: PAPEL | C36: =VLOOKUP($C$32&"-"&B36,Planilha3!$A:$D,4,FALSE) -> 0.5 | D36: =C36*valor_a_Ser_investido_no_mes -> 650
B37: TIJOLO | C37: =VLOOKUP($C$32&"-"&B37,Planilha3!$A:$D,4,FALSE) -> 0.1 | D37: =C37*valor_a_Ser_investido_no_mes -> 130
B38: HIBRIDO | C38: =VLOOKUP($C$32&"-"&B38,Planilha3!$A:$D,4,FALSE) -> 0.05 | D38: =C38*valor_a_Ser_investido_no_mes -> 65
B39: FOF's | C39: =VLOOKUP($C$32&"-"&B39,Planilha3!$A:$D,4,FALSE) -> 0.05 | D39: =C39*valor_a_Ser_investido_no_mes -> 65
B40: DESENVOLVIMENTO | C40: =VLOOKUP($C$32&"-"&B40,Planilha3!$A:$D,4,FALSE) -> 0.2 | D40: =C40*valor_a_Ser_investido_no_mes -> 260
B41: HOTELARIAS | C41: =VLOOKUP($C$32&"-"&B41,Planilha3!$A:$D,4,FALSE) -> 0.1 | D41: =C41*valor_a_Ser_investido_no_mes -> 130
C42: valor total | D42: =SUM(D36:D41) -> 1300

Sheet Planilha3
A3: CHAVE COMPOSTA | B3: PERFIL | C3: TIPO DE FIL | D3: %
A4: =B4&"-"&C4 -> CONSERVADOR-PAPEL | B4: CONSERVADOR | C4: PAPEL | D4: 0.3 | G4: CONSERVADOR-PAPEL | H4: =VLOOKUP(G4,$A:$D,4,FALSE) -> 0.3
A5: =B5&"-"&C5 -> CONSERVADOR-TIJOLO | B5: CONSERVADOR | C5: TIJOLO | D5: 0.5
A6: =B6&"-"&C6 -> CONSERVADOR-HIBRIDO | B6: CONSERVADOR | C6: HIBRIDO | D6: 0.1
A7: =B7&"-"&C7 -> CONSERVADOR-FOF's | B7: CONSERVADOR | C7: FOF's | D7: 0.1
A8: =B8&"-"&C8 -> CONSERVADOR-DESENVOLVIMENTO | B8: CONSERVADOR | C8: DESENVOLVIMENTO | D8: 0
A9: =B9&"-"&C9 -> CONSERVADOR-HOTELARIAS | B9: CONSERVADOR | C9: HOTELARIAS | D9: 0
A10: =B10&"-"&C10 -> AGRESSIVO-PAPEL | B10: AGRESSIVO | C10: PAPEL | D10: 0.5
A11: =B11&"-"&C11 -> AGRESSIVO-TIJOLO | B11: AGRESSIVO | C11: TIJOLO | D11: 0.1
A12: =B12&"-"&C12 -> AGRESSIVO-HIBRIDO | B12: AGRESSIVO | C12: HIBRIDO | D12: 0.05
A13: =B13&"-"&C13 -> AGRESSIVO-FOF's | B13: AGRESSIVO | C13: FOF's | D13: 0.05
A14: =B14&"-"&C14 -> AGRESSIVO-DESENVOLVIMENTO | B14: AGRESSIVO | C14: DESENVOLVIMENTO | D14: 0.2
A15: =B15&"-"&C15 -> AGRESSIVO-HOTELARIAS | B15: AGRESSIVO | C15: HOTELARIAS | D15: 0.1
A16: =B16&"-"&C16 -> MODERADO-PAPEL | B16: MODERADO | C16: PAPEL | D16: 0.1
... A21: =B21&"-"&C21 -> MODERADO-HOTELARIAS | B21: MODERADO | C21: HOTELARIAS | D21: 0.05
